group_by_attr/__init__.py
group_by_attr-1.0.1.dist-info/top_level.txt
group_by_attr-1.0.1.dist-info/METADATA
group_by_attr-1.0.1.dist-info/DESCRIPTION.rst
group_by_attr-1.0.1.dist-info/metadata.json
group_by_attr-1.0.1.dist-info/WHEEL
group_by_attr-1.0.1.dist-info/RECORD
