Metadata-Version: 2.0
Name: group-by-attr
Version: 1.0.1
Summary: Group items in a sequence by the value of a shared attribute.
Home-page: https://github.com/themattrix/python-group-by-attr
Author: Matthew Tardiff
Author-email: mattrix@gmail.com
License: MIT
Platform: UNKNOWN
Classifier: License :: OSI Approved :: MIT License
Classifier: Programming Language :: Python :: 2
Classifier: Programming Language :: Python :: 2.6
Classifier: Programming Language :: Python :: 2.7
Classifier: Programming Language :: Python :: 3
Classifier: Programming Language :: Python :: 3.2
Classifier: Programming Language :: Python :: 3.3
Classifier: Programming Language :: Python :: 3.4
Classifier: Programming Language :: Python :: Implementation :: CPython
Classifier: Programming Language :: Python :: Implementation :: PyPy
